Workbook

Sheet Read Me
A3: Financial Due Diligence Case Study
A5: Company | B5: Marico Limited
A6: Industry | B6: Consumer Goods
A7: Analysis Type | B7: Financial Due Diligence
A8: Currency | B8: INR (₹ crore)
A9: Status | B9: In Progress
A10: Data status | B10: Initial figures from consolidated statements screenshot; verify against official report before final use.
A14: Financial Due Diligence Conclusion — Marico Limited
A16: Marico Limited demonstrated strong revenue growth and improved operating cash generation in FY2025–26. However, profitability grew more slowly than revenue, resulting in a decline in net profit margin. Total liabilities increased faster than total assets, and the current ratio declined from 2.07x to 1.43x, highlighting areas that require further investigation.
A18: Overall, the available financial indicators show business growth alongside emerging liquidity and margin considerations. Before reaching a final due diligence decision, further review of working-capital movements, liability composition, expense drivers, and supporting financial statement notes is recommended.
A20: Scope limitation: This preliminary assessment is based on selected consolidated financial statement figures for FY2024–25 and FY2025–26. It is not a complete investment recommendation or audit.

Sheet Historical Financials
A1: Financial Metric | B1: FY2024-25 | C1: FY2025-26 | D1: Source / Notes
A2: Revenue from Operations | B2: 10831 | C2: 13611 | D2: Consolidated Annual Report FY26
A3: Total Income | B3: 11039 | C3: 13815 | D3: Consolidated Annual Report FY26
A4: Profit Before Tax | B4: 2116 | C4: 2277 | D4: Consolidated Annual Report FY26
A5: Profit for the Year | B5: 1658 | C5: 1813 | D5: Consolidated Annual Report FY26
A6: Total Assets | B6: 8332 | C6: 10075 | D6: Consolidated Annual Report FY26
A7: Total Liabilities | B7: 4066 | C7: 5581 | D7: Consolidated Annual Report FY26
A8: Total Equity | B8: 4266 | C8: 4494 | D8: Consolidated Annual Report FY26
A9: Net cash from operating activities | B9: 1363 | C9: 2084 | D9: Consolidated Annual Report FY26
A10: Current Assets | B10: 5077 | C10: 5860 | D10: Marico Integrated Annual Report FY2025–26, p. 376 — Consolidated Balance Sheet
A11: Current Liabilities | B11: 2455 | C11: 4101 | D11: Marico Integrated Annual Report FY2025–26, p. 376 — Consolidated Balance Sheet

Sheet Ratio Analysis
A1: Ratio / Metric | B1: FY2024-25 | C1: FY2025-26 | D1: Interpretation
A2: Revenue growth | B2: =('Historical Financials'!C2-'Historical Financials'!B2)/'Historical Financials'!B2 -> 0.25667067 | C2: ='Historical Financials'!C2/'Historical Financials'!B2-1 -> 0.25667067 | D2: FY26 revenue growth vs FY25
A3: Profit before tax margin | B3: ='Historical Financials'!B4/'Historical Financials'!B2 -> 0.19536516 | C3: ='Historical Financials'!C4/'Historical Financials'!C2 -> 0.16729116 | D3: Profit before tax as % of revenue
A4: Net profit margin | B4: ='Historical Financials'!B5/'Historical Financials'!B2 -> 0.15307912 | C4: ='Historical Financials'!C5/'Historical Financials'!C2 -> 0.13320109 | D4: Profit for the year as % of revenue
A5: Liabilities to assets | B5: ='Historical Financials'!B7/'Historical Financials'!B6 -> 0.48799808 | C5: ='Historical Financials'!C7/'Historical Financials'!C6 -> 0.55394541 | D5: Share of assets funded by liabilities
A6: Equity to assets | B6: ='Historical Financials'!B8/'Historical Financials'!B6 -> 0.51200192 | C6: ='Historical Financials'!C8/'Historical Financials'!C6 -> 0.44605459 | D6: Share of assets funded by equity
A7: Total assets growth | B7: =('Historical Financials'!C6-'Historical Financials'!B6)/'Historical Financials'!B6 -> 0.20919347 | C7: ='Historical Financials'!C6/'Historical Financials'!B6-1 -> 0.20919347 | D7: Growth in total assets
A8: Total liabilities growth | B8: =('Historical Financials'!C7-'Historical Financials'!B7)/'Historical Financials'!B7 -> 0.37260207 | C8: ='Historical Financials'!C7/'Historical Financials'!B7-1 -> 0.37260207 | D8: Growth in total liabilities
A9: Operating Cash Flow | B9: ='Historical Financials'!B9/'Historical Financials'!B5 -> 0.82207479 | C9: ='Historical Financials'!C9/'Historical Financials'!C5 -> 1.149476
A10: Net Profit Margin | B10: ='Historical Financials'!B5/'Historical Financials'!B2 -> 0.15307912 | C10: ='Historical Financials'!C5/'Historical Financials'!C2 -> 0.13320109
A11: Current Ratio | B11: ='Historical Financials'!B10/'Historical Financials'!B11 -> 2.0680244 | C11: ='Historical Financials'!C10/'Historical Financials'!C11 -> 1.4289198
A12: Debt-to-Equity Ratio | B12: ='Historical Financials'!B7/'Historical Financials'!B8 -> 0.95311767 | C12: ='Historical Financials'!C7/'Historical Financials'!C8 -> 1.2418781
A13: Return on Equity (ROE) | B13: ='Historical Financials'!B5/'Historical Financials'!B8 -> 0.38865448 | C13: ='Historical Financials'!C5/'Historical Financials'!C8 -> 0.40342679
A14: Operating Cash Flow to Net Profit | B14: ='Historical Financials'!B9/'Historical Financials'!B5 -> 0.82207479 | C14: ='Historical Financials'!C9/'Historical Financials'!C5 -> 1.149476
A15: Total Liabilities Growth | C15: =('Historical Financials'!C7-'Historical Financials'!B7)/'Historical Financials'!B7 -> 0.37260207
A16: Total Assets Growth | C16: =('Historical Financials'!C6-'Historical Financials'!B6)/'Historical Financials'!B6 -> 0.20919347

Sheet Red Flags
A1: Area to Review | B1: Evidence / Metric | C1: Initial Observation | D1: Status | E1: Next Check
A2: Liabilities growth | B2: Total liabilities: ₹4,066 cr (FY25) to ₹5,581 cr (FY26) | C2: Total liabilities increased 37.3%; current liabilities rose from ₹2,455 cr to ₹4,101 cr. Investigate the categories driving this increase. | D2: Investigate | E2: Compare borrowings, trade payables, provisions and other liabilities in notes.
A3: Profitability | B3: PBT: ₹2,116 cr to ₹2,277 cr; profit for year: ₹1,658 cr to ₹1,813 cr | C3: Both reported profit measures increased year over year. | D3: No immediate issue from these figures | E3: Review margins and cash flow before concluding.
A4: Data verification | B4: Figures currently transcribed from user-provided screenshot | C4: Key figures cross-checked against Marico's official FY26 consolidated balance sheet and financial results. | D4: Verified — for figures checked | E4: Use consolidated statements, not subsidiary-only statements.
A5: Current liabilities breakdown | B5: FY25 to FY26: Total current liabilities increased from ₹2,455 cr to ₹4,101 cr. Other current liabilities increased from ₹232 cr to ₹1,585 cr, while trade payables to other creditors increased from ₹1,217 cr to ₹1,488 cr. Figures require verification against the relevant consolidated financial statement notes. | C5: Current liabilities increased from ₹2,455 crore to ₹4,101 crore, with a notable increase in other current liabilities. | D5: Investigate | E5: What explains the increase in other current liabilities, and is it recurring or one-off?
A6: Other Current Liabilities | B6: Other current liabilities increased from ₹232 crore in FY2024–25 to ₹1,585 crore in FY2025–26. | C6: The substantial increase requires investigation. The exact components and business reasons for the increase have not yet been verified from the FY2025–26 consolidated financial-statement notes. | D6: Investigate | E6: Review the FY2025–26 consolidated note for other current liabilities, compare each component with FY2024–25, and determine whether the increase relates to normal business operations, timing differences, one-off items, or another cause.
A7: Total Assets Growth | B7: Marico’s total assets increased by approximately 20.9% from FY2024–25 to FY2025–26, while total liabilities increased by approximately 37.3%. Liabilities grew faster than assets, so the increase warrants further investigation into the sources of funding and changes in the balance sheet. | C7: Positive Observation | D7: Investigate | E7: Review expense increases and reasons for margin decline
A8: Revenue and Profitability | B8: Revenue +25.7%; PBT +7.6%; Profit +9.3% | C8: Revenue grew faster than profits. Net profit margin declined from 15.3% to 13.3%. | D8: Investigate | E8: Review the increase in current liabilities and working-capital movements.
A9: Short-term Liquidity | B9: Current ratio declined from 2.07x to 1.43x; current liabilities increased 67.1%. | C9: The short-term liquidity cushion has decreased. | D9: Positive | E9: Review working-capital movements and confirm the cash flow trend is sustainable.
A10: Cash Flow Quality | B10: Operating cash flow increased from ₹1,363 cr to ₹2,084 cr; cash flow/net profit improved from 82.2% to 115.0%. | C10: Cash generation improved and exceeded reported profit in FY2025–26.

Sheet Dashboard
A1: Marico Limited — Financial Due Diligence Dashboard
A3: Metric | B3: FY2024-25 | C3: FY2025-26 | D3: Change
A4: Revenue from Operations | B4: ='Historical Financials'!B2 -> 10831 | C4: ='Historical Financials'!C2 -> 13611 | D4: =C4/B4-1 -> 0.25667067
A5: Profit Before Tax | B5: ='Historical Financials'!B4 -> 2116 | C5: ='Historical Financials'!C4 -> 2277 | D5: =C5/B5-1 -> 0.076086957
A6: Profit for the Year | B6: ='Historical Financials'!B5 -> 1658 | C6: ='Historical Financials'!C5 -> 1813 | D6: =C6/B6-1 -> 0.093486128
A7: Total Assets | B7: ='Historical Financials'!B6 -> 8332 | C7: ='Historical Financials'!C6 -> 10075 | D7: =C7/B7-1 -> 0.20919347
A8: Total Liabilities | B8: ='Historical Financials'!B7 -> 4066 | C8: ='Historical Financials'!C7 -> 5581 | D8: =C8/B8-1 -> 0.37260207
A9: Total Equity | B9: ='Historical Financials'!B8 -> 4266 | C9: ='Historical Financials'!C8 -> 4494 | D9: =C9/B9-1 -> 0.053445851
A10: Current Assets | B10: 5077 | C10: 5860 | D10: 0.154
A11: Current Liabilities | B11: 2455 | C11: 4101 | D11: 0.671
A12: Current Ratio | B12: 2.07 | C12: 1.43 | D12: Decreased
A13: Net Profit Margin | B13: 0.153 | C13: 0.133 | D13: Decreased
A14: Operating Cash Flow / Net Profit | B14: 0.822 | C14: 1.15 | D14: Improved
